structuretimers/__init__.py
structuretimers/admin.py
structuretimers/app_settings.py
structuretimers/apps.py
structuretimers/auth_hooks.py
structuretimers/constants.py
structuretimers/forms.py
structuretimers/managers.py
structuretimers/models.py
structuretimers/tasks.py
structuretimers/urls.py
structuretimers/views.py
structuretimers/locale/django.pot
structuretimers/locale/de/LC_MESSAGES/django.po
structuretimers/locale/en/LC_MESSAGES/django.po
structuretimers/locale/es/LC_MESSAGES/django.po
structuretimers/locale/fr_FR/LC_MESSAGES/django.po
structuretimers/locale/it_IT/LC_MESSAGES/django.po
structuretimers/locale/ja/LC_MESSAGES/django.po
structuretimers/locale/ko/LC_MESSAGES/django.po
structuretimers/locale/ko_KR/LC_MESSAGES/django.po
structuretimers/locale/ru/LC_MESSAGES/django.po
structuretimers/locale/zh_Hans/LC_MESSAGES/django.po
structuretimers/management/commands/__init__.py
structuretimers/management/commands/structuretimers_load_eve.py
structuretimers/management/commands/structuretimers_migrate_timers.py
structuretimers/migrations/0001_initial.py
structuretimers/migrations/0002_distances_from_staging.py
structuretimers/migrations/0003_add_preliminary_timers.py
structuretimers/migrations/0004_add_space_type_and_region_filters.py
structuretimers/migrations/0005_alter_notificationrule_exclude_space_types_and_more.py
structuretimers/migrations/0006_add_theft_timer_type.py
structuretimers/migrations/__init__.py
structuretimers/static/structuretimers/css/global.css
structuretimers/static/structuretimers/css/timer_edit.css
structuretimers/static/structuretimers/css/timer_list.css
structuretimers/static/structuretimers/img/Spinner-1s-64px-dark.gif
structuretimers/static/structuretimers/img/Spinner-1s-64px-light.gif
structuretimers/static/structuretimers/img/structuretimers_logo.png
structuretimers/static/structuretimers/js/timer_edit.js
structuretimers/static/structuretimers/js/timer_list.js
aa_structuretimers-2.1.0.dist-info/licenses/LICENSE
aa_structuretimers-2.1.0.dist-info/WHEEL
aa_structuretimers-2.1.0.dist-info/METADATA
aa_structuretimers-2.1.0.dist-info/RECORD
