Metadata-Version: 2.4
Name: aa-structuretimers
Version: 2.1.0
Summary: An app for keeping track of Eve Online structure timers
Author-email: Erik Kalkoken <kalkoken87@gmail.com>
Requires-Python: >=3.8
Classifier: Environment :: Web Environment
Classifier: Framework :: Django
Classifier: Framework :: Django :: 4.2
Classifier: Intended Audience :: End Users/Desktop
Classifier: License :: OSI Approved :: MIT License
Classifier: Operating System :: OS Independent
Classifier: Programming Language :: Python
Classifier: Programming Language :: Python :: 3.8
Classifier: Programming Language :: Python :: 3.9
Classifier: Programming Language :: Python :: 3.10
Classifier: Programming Language :: Python :: 3.11
Classifier: Programming Language :: Python :: 3.12
Classifier: Topic :: Internet :: WWW/HTTP
Classifier: Topic :: Internet :: WWW/HTTP :: Dynamic Content
License-File: LICENSE
Requires-Dist: allianceauth-app-utils>=1.27
Requires-Dist: allianceauth>=4,<5
Requires-Dist: dhooks_lite>=1.0.0
Requires-Dist: django-eveuniverse>=0.16
Requires-Dist: django-multiselectfield
Requires-Dist: redis-simple-mq>=0.4
Requires-Dist: requests
Requires-Dist: puremagic
Project-URL: Changelog, https://gitlab.com/ErikKalkoken/aa-structuretimers/-/blob/master/CHANGELOG.md
Project-URL: Homepage, https://gitlab.com/ErikKalkoken/aa-structuretimers
Project-URL: Source, https://gitlab.com/ErikKalkoken/aa-structuretimers
Project-URL: Tracker, https://gitlab.com/ErikKalkoken/aa-structuretimers/-/issues
